[
    {
        "id":1,
        "name":"Honda ADV 155",
        "img":"https://litusautomobiles.com/wp-content/uploads/2022/02/zMZAsset-16.png",
        "price":10000,
        "description":"Honda the Japanese brand equipped this bike with advanced features, armored with adventure-ready style.v ",
        "sepliarName":"rasel",
        "quantity":1
    },
    {
        "id":2,
        "name":"Honda ADV 155",
        "img":"https://litusautomobiles.com/wp-content/uploads/2022/02/zMZAsset-16.png",
        "price":10000,
        "description":"Honda the Japanese brand equipped this bike with advanced features, armored with adventure-ready style.v ",
        "sepliarName":"rasel",
        "quantity":1
    },
    {
        "id":3,
        "name":"Honda ADV 155",
        "img":"https://litusautomobiles.com/wp-content/uploads/2022/02/zMZAsset-16.png",
        "price":10000,
        "description":"Honda the Japanese brand equipped this bike with advanced features, armored with adventure-ready style.v ",
        "sepliarName":"rasel",
        "quantity":1
    },
    {
        "id":4,
        "name":"Honda ADV 155",
        "img":"https://litusautomobiles.com/wp-content/uploads/2022/02/zMZAsset-16.png",
        "price":10000,
        "description":"Honda the Japanese brand equipped this bike with advanced features, armored with adventure-ready style.v ",
        "sepliarName":"rasel",
        "quantity":1
    },
    {
        "id":5,
        "name":"Honda ADV 155",
        "img":"https://litusautomobiles.com/wp-content/uploads/2022/02/zMZAsset-16.png",
        "price":10000,
        "description":"Honda the Japanese brand equipped this bike with advanced features, armored with adventure-ready style.v ",
        "sepliarName":"rasel",
        "quantity":1
    },
    {
        "id":6,
        "name":"Honda ADV 155",
        "img":"https://litusautomobiles.com/wp-content/uploads/2022/02/zMZAsset-16.png",
        "price":10000,
        "description":"Honda the Japanese brand equipped this bike with advanced features, armored with adventure-ready style.v ",
        "sepliarName":"rasel",
        "quantity":1
    },
    {
        "id":7,
        "name":"Honda ADV 155",
        "img":"https://litusautomobiles.com/wp-content/uploads/2022/02/zMZAsset-16.png",
        "price":10000,
        "description":"Honda the Japanese brand equipped this bike with advanced features, armored with adventure-ready style.v ",
        "sepliarName":"rasel",
        "quantity":1
    }
]